{
  "page": 187,
  "verses": [
    {
      "sura": 9,
      "ayah": 1,
      "glyphs": [
        {
          "line": 2,
          "min_x": 1083,
          "max_x": 1207,
          "min_y": 164,
          "max_y": 251
        },
        {
          "line": 2,
          "min_x": 1018,
          "max_x": 1081,
          "min_y": 172,
          "max_y": 251
        },
        {
          "line": 2,
          "min_x": 948,
          "max_x": 1013,
          "min_y": 172,
          "max_y": 253
        },
        {
          "line": 2,
          "min_x": 770,
          "max_x": 941,
          "min_y": 170,
          "max_y": 248
        },
        {
          "line": 2,
          "min_x": 713,
          "max_x": 768,
          "min_y": 169,
          "max_y": 256
        },
        {
          "line": 2,
          "min_x": 607,
          "max_x": 704,
          "min_y": 159,
          "max_y": 253
        },
        {
          "line": 2,
          "min_x": 436,
          "max_x": 602,
          "min_y": 156,
          "max_y": 268
        },
        {
          "line": 2,
          "min_x": 371,
          "max_x": 430,
          "min_y": 174,
          "max_y": 251
        },
        {
          "line": 2,
          "min_x": 181,
          "max_x": 367,
          "min_y": 169,
          "max_y": 266
        },
        {
          "line": 2,
          "min_x": 65,
          "max_x": 168,
          "min_y": 162,
          "max_y": 257
        }
      ]
    },
    {
      "sura": 9,
      "ayah": 2,
      "glyphs": [
        {
          "line": 3,
          "min_x": 1025,
          "max_x": 1207,
          "min_y": 302,
          "max_y": 385
        },
        {
          "line": 3,
          "min_x": 972,
          "max_x": 1018,
          "min_y": 315,
          "max_y": 387
        },
        {
          "line": 3,
          "min_x": 815,
          "max_x": 961,
          "min_y": 291,
          "max_y": 390
        },
        {
          "line": 3,
          "min_x": 681,
          "max_x": 804,
          "min_y": 296,
          "max_y": 384
        },
        {
          "line": 3,
          "min_x": 559,
          "max_x": 672,
          "min_y": 293,
          "max_y": 407
        },
        {
          "line": 3,
          "min_x": 397,
          "max_x": 559,
          "min_y": 298,
          "max_y": 386
        },
        {
          "line": 3,
          "min_x": 287,
          "max_x": 386,
          "min_y": 286,
          "max_y": 383
        },
        {
          "line": 3,
          "min_x": 213,
          "max_x": 286,
          "min_y": 301,
          "max_y": 383
        },
        {
          "line": 3,
          "min_x": 63,
          "max_x": 213,
          "min_y": 303,
          "max_y": 398
        },
        {
          "line": 4,
          "min_x": 1143,
          "max_x": 1209,
          "min_y": 437,
          "max_y": 520
        },
        {
          "line": 4,
          "min_x": 1136,
          "max_x": 1136,
          "min_y": 417,
          "max_y": 443
        },
        {
          "line": 4,
          "min_x": 1057,
          "max_x": 1132,
          "min_y": 429,
          "max_y": 515
        },
        {
          "line": 4,
          "min_x": 986,
          "max_x": 1054,
          "min_y": 436,
          "max_y": 502
        },
        {
          "line": 4,
          "min_x": 869,
          "max_x": 979,
          "min_y": 426,
          "max_y": 531
        },
        {
          "line": 4,
          "min_x": 673,
          "max_x": 862,
          "min_y": 431,
          "max_y": 532
        },
        {
          "line": 4,
          "min_x": 562,
          "max_x": 664,
          "min_y": 428,
          "max_y": 523
        }
      ]
    },
    {
      "sura": 9,
      "ayah": 3,
      "glyphs": [
        {
          "line": 4,
          "min_x": 424,
          "max_x": 563,
          "min_y": 426,
          "max_y": 512
        },
        {
          "line": 4,
          "min_x": 308,
          "max_x": 418,
          "min_y": 446,
          "max_y": 518
        },
        {
          "line": 4,
          "min_x": 235,
          "max_x": 300,
          "min_y": 439,
          "max_y": 521
        },
        {
          "line": 4,
          "min_x": 62,
          "max_x": 229,
          "min_y": 438,
          "max_y": 519
        },
        {
          "line": 5,
          "min_x": 1150,
          "max_x": 1209,
          "min_y": 565,
          "max_y": 655
        },
        {
          "line": 5,
          "min_x": 1019,
          "max_x": 1139,
          "min_y": 563,
          "max_y": 652
        },
        {
          "line": 5,
          "min_x": 941,
          "max_x": 1007,
          "min_y": 574,
          "max_y": 666
        },
        {
          "line": 5,
          "min_x": 834,
          "max_x": 933,
          "min_y": 563,
          "max_y": 670
        },
        {
          "line": 5,
          "min_x": 618,
          "max_x": 822,
          "min_y": 561,
          "max_y": 658
        },
        {
          "line": 5,
          "min_x": 564,
          "max_x": 611,
          "min_y": 558,
          "max_y": 640
        },
        {
          "line": 5,
          "min_x": 488,
          "max_x": 554,
          "min_y": 565,
          "max_y": 636
        },
        {
          "line": 5,
          "min_x": 347,
          "max_x": 479,
          "min_y": 574,
          "max_y": 666
        },
        {
          "line": 5,
          "min_x": 279,
          "max_x": 339,
          "min_y": 576,
          "max_y": 653
        },
        {
          "line": 5,
          "min_x": 67,
          "max_x": 269,
          "min_y": 565,
          "max_y": 665
        },
        {
          "line": 5,
          "min_x": 61,
          "max_x": 65,
          "min_y": 547,
          "max_y": 572
        },
        {
          "line": 6,
          "min_x": 1048,
          "max_x": 1210,
          "min_y": 691,
          "max_y": 782
        },
        {
          "line": 6,
          "min_x": 1056,
          "max_x": 1044,
          "min_y": 676,
          "max_y": 700
        },
        {
          "line": 6,
          "min_x": 972,
          "max_x": 1040,
          "min_y": 700,
          "max_y": 790
        },
        {
          "line": 6,
          "min_x": 852,
          "max_x": 958,
          "min_y": 697,
          "max_y": 804
        },
        {
          "line": 6,
          "min_x": 748,
          "max_x": 841,
          "min_y": 703,
          "max_y": 786
        },
        {
          "line": 6,
          "min_x": 654,
          "max_x": 744,
          "min_y": 700,
          "max_y": 786
        },
        {
          "line": 6,
          "min_x": 501,
          "max_x": 652,
          "min_y": 691,
          "max_y": 796
        },
        {
          "line": 6,
          "min_x": 484,
          "max_x": 489,
          "min_y": 677,
          "max_y": 703
        },
        {
          "line": 6,
          "min_x": 401,
          "max_x": 485,
          "min_y": 713,
          "max_y": 791
        },
        {
          "line": 6,
          "min_x": 251,
          "max_x": 391,
          "min_y": 690,
          "max_y": 806
        },
        {
          "line": 6,
          "min_x": 62,
          "max_x": 241,
          "min_y": 694,
          "max_y": 783
        },
        {
          "line": 7,
          "min_x": 1097,
          "max_x": 1210,
          "min_y": 825,
          "max_y": 935
        },
        {
          "line": 7,
          "min_x": 1006,
          "max_x": 1085,
          "min_y": 831,
          "max_y": 918
        },
        {
          "line": 7,
          "min_x": 814,
          "max_x": 1002,
          "min_y": 837,
          "max_y": 930
        },
        {
          "line": 7,
          "min_x": 734,
          "max_x": 801,
          "min_y": 833,
          "max_y": 922
        },
        {
          "line": 7,
          "min_x": 725,
          "max_x": 724,
          "min_y": 812,
          "max_y": 838
        },
        {
          "line": 7,
          "min_x": 594,
          "max_x": 720,
          "min_y": 837,
          "max_y": 931
        },
        {
          "line": 7,
          "min_x": 490,
          "max_x": 592,
          "min_y": 820,
          "max_y": 917
        },
        {
          "line": 7,
          "min_x": 371,
          "max_x": 477,
          "min_y": 828,
          "max_y": 918
        },
        {
          "line": 7,
          "min_x": 174,
          "max_x": 363,
          "min_y": 833,
          "max_y": 929
        },
        {
          "line": 7,
          "min_x": 64,
          "max_x": 160,
          "min_y": 822,
          "max_y": 927
        },
        {
          "line": 8,
          "min_x": 1107,
          "max_x": 1209,
          "min_y": 960,
          "max_y": 1055
        }
      ]
    },
    {
      "sura": 9,
      "ayah": 4,
      "glyphs": [
        {
          "line": 8,
          "min_x": 1013,
          "max_x": 1108,
          "min_y": 957,
          "max_y": 1054
        },
        {
          "line": 8,
          "min_x": 837,
          "max_x": 1001,
          "min_y": 954,
          "max_y": 1047
        },
        {
          "line": 8,
          "min_x": 645,
          "max_x": 828,
          "min_y": 954,
          "max_y": 1060
        },
        {
          "line": 8,
          "min_x": 577,
          "max_x": 637,
          "min_y": 976,
          "max_y": 1051
        },
        {
          "line": 8,
          "min_x": 362,
          "max_x": 571,
          "min_y": 963,
          "max_y": 1065
        },
        {
          "line": 8,
          "min_x": 309,
          "max_x": 357,
          "min_y": 958,
          "max_y": 1074
        },
        {
          "line": 8,
          "min_x": 263,
          "max_x": 304,
          "min_y": 964,
          "max_y": 1073
        },
        {
          "line": 8,
          "min_x": 61,
          "max_x": 255,
          "min_y": 955,
          "max_y": 1066
        },
        {
          "line": 9,
          "min_x": 1108,
          "max_x": 1209,
          "min_y": 1106,
          "max_y": 1180
        },
        {
          "line": 9,
          "min_x": 1019,
          "max_x": 1098,
          "min_y": 1098,
          "max_y": 1198
        },
        {
          "line": 9,
          "min_x": 835,
          "max_x": 1005,
          "min_y": 1095,
          "max_y": 1192
        },
        {
          "line": 9,
          "min_x": 681,
          "max_x": 822,
          "min_y": 1089,
          "max_y": 1201
        },
        {
          "line": 9,
          "min_x": 566,
          "max_x": 666,
          "min_y": 1092,
          "max_y": 1166
        },
        {
          "line": 9,
          "min_x": 436,
          "max_x": 555,
          "min_y": 1089,
          "max_y": 1185
        },
        {
          "line": 9,
          "min_x": 298,
          "max_x": 421,
          "min_y": 1102,
          "max_y": 1197
        },
        {
          "line": 9,
          "min_x": 124,
          "max_x": 291,
          "min_y": 1101,
          "max_y": 1181
        },
        {
          "line": 9,
          "min_x": 62,
          "max_x": 119,
          "min_y": 1098,
          "max_y": 1181
        },
        {
          "line": 10,
          "min_x": 1073,
          "max_x": 1207,
          "min_y": 1228,
          "max_y": 1329
        },
        {
          "line": 10,
          "min_x": 1068,
          "max_x": 1062,
          "min_y": 1220,
          "max_y": 1244
        },
        {
          "line": 10,
          "min_x": 1013,
          "max_x": 1058,
          "min_y": 1234,
          "max_y": 1319
        },
        {
          "line": 10,
          "min_x": 942,
          "max_x": 1006,
          "min_y": 1236,
          "max_y": 1301
        },
        {
          "line": 10,
          "min_x": 831,
          "max_x": 932,
          "min_y": 1233,
          "max_y": 1314
        },
        {
          "line": 10,
          "min_x": 667,
          "max_x": 823,
          "min_y": 1225,
          "max_y": 1316
        },
        {
          "line": 10,
          "min_x": 554,
          "max_x": 656,
          "min_y": 1226,
          "max_y": 1321
        }
      ]
    },
    {
      "sura": 9,
      "ayah": 5,
      "glyphs": [
        {
          "line": 10,
          "min_x": 458,
          "max_x": 555,
          "min_y": 1232,
          "max_y": 1321
        },
        {
          "line": 10,
          "min_x": 325,
          "max_x": 448,
          "min_y": 1234,
          "max_y": 1330
        },
        {
          "line": 10,
          "min_x": 166,
          "max_x": 318,
          "min_y": 1224,
          "max_y": 1318
        },
        {
          "line": 10,
          "min_x": 61,
          "max_x": 166,
          "min_y": 1226,
          "max_y": 1327
        },
        {
          "line": 11,
          "min_x": 1066,
          "max_x": 1205,
          "min_y": 1361,
          "max_y": 1448
        },
        {
          "line": 11,
          "min_x": 839,
          "max_x": 1050,
          "min_y": 1365,
          "max_y": 1462
        },
        {
          "line": 11,
          "min_x": 703,
          "max_x": 827,
          "min_y": 1362,
          "max_y": 1447
        },
        {
          "line": 11,
          "min_x": 464,
          "max_x": 690,
          "min_y": 1349,
          "max_y": 1445
        },
        {
          "line": 11,
          "min_x": 283,
          "max_x": 459,
          "min_y": 1360,
          "max_y": 1445
        },
        {
          "line": 11,
          "min_x": 64,
          "max_x": 278,
          "min_y": 1363,
          "max_y": 1477
        },
        {
          "line": 12,
          "min_x": 1044,
          "max_x": 1209,
          "min_y": 1499,
          "max_y": 1578
        },
        {
          "line": 12,
          "min_x": 941,
          "max_x": 1029,
          "min_y": 1497,
          "max_y": 1600
        },
        {
          "line": 12,
          "min_x": 779,
          "max_x": 932,
          "min_y": 1486,
          "max_y": 1576
        },
        {
          "line": 12,
          "min_x": 610,
          "max_x": 769,
          "min_y": 1504,
          "max_y": 1589
        },
        {
          "line": 12,
          "min_x": 613,
          "max_x": 600,
          "min_y": 1484,
          "max_y": 1508
        },
        {
          "line": 12,
          "min_x": 531,
          "max_x": 596,
          "min_y": 1504,
          "max_y": 1590
        },
        {
          "line": 12,
          "min_x": 422,
          "max_x": 518,
          "min_y": 1498,
          "max_y": 1579
        },
        {
          "line": 12,
          "min_x": 244,
          "max_x": 408,
          "min_y": 1490,
          "max_y": 1580
        },
        {
          "line": 12,
          "min_x": 59,
          "max_x": 229,
          "min_y": 1498,
          "max_y": 1580
        },
        {
          "line": 13,
          "min_x": 1082,
          "max_x": 1205,
          "min_y": 1634,
          "max_y": 1716
        },
        {
          "line": 13,
          "min_x": 874,
          "max_x": 1073,
          "min_y": 1631,
          "max_y": 1718
        },
        {
          "line": 13,
          "min_x": 744,
          "max_x": 868,
          "min_y": 1610,
          "max_y": 1712
        },
        {
          "line": 13,
          "min_x": 576,
          "max_x": 741,
          "min_y": 1632,
          "max_y": 1728
        },
        {
          "line": 13,
          "min_x": 570,
          "max_x": 569,
          "min_y": 1617,
          "max_y": 1641
        },
        {
          "line": 13,
          "min_x": 518,
          "max_x": 565,
          "min_y": 1628,
          "max_y": 1722
        },
        {
          "line": 13,
          "min_x": 447,
          "max_x": 513,
          "min_y": 1631,
          "max_y": 1699
        },
        {
          "line": 13,
          "min_x": 310,
          "max_x": 434,
          "min_y": 1629,
          "max_y": 1714
        },
        {
          "line": 13,
          "min_x": 183,
          "max_x": 311,
          "min_y": 1633,
          "max_y": 1716
        },
        {
          "line": 13,
          "min_x": 66,
          "max_x": 169,
          "min_y": 1625,
          "max_y": 1720
        }
      ]
    },
    {
      "sura": 9,
      "ayah": 6,
      "glyphs": [
        {
          "line": 14,
          "min_x": 1120,
          "max_x": 1209,
          "min_y": 1772,
          "max_y": 1852
        },
        {
          "line": 14,
          "min_x": 1021,
          "max_x": 1110,
          "min_y": 1755,
          "max_y": 1831
        },
        {
          "line": 14,
          "min_x": 961,
          "max_x": 1020,
          "min_y": 1767,
          "max_y": 1848
        },
        {
          "line": 14,
          "min_x": 659,
          "max_x": 950,
          "min_y": 1765,
          "max_y": 1862
        },
        {
          "line": 14,
          "min_x": 435,
          "max_x": 642,
          "min_y": 1764,
          "max_y": 1842
        },
        {
          "line": 14,
          "min_x": 300,
          "max_x": 418,
          "min_y": 1750,
          "max_y": 1857
        },
        {
          "line": 14,
          "min_x": 203,
          "max_x": 291,
          "min_y": 1760,
          "max_y": 1848
        },
        {
          "line": 14,
          "min_x": 64,
          "max_x": 193,
          "min_y": 1771,
          "max_y": 1867
        },
        {
          "line": 15,
          "min_x": 1119,
          "max_x": 1209,
          "min_y": 1894,
          "max_y": 1995
        },
        {
          "line": 15,
          "min_x": 1045,
          "max_x": 1112,
          "min_y": 1899,
          "max_y": 1978
        },
        {
          "line": 15,
          "min_x": 973,
          "max_x": 1039,
          "min_y": 1894,
          "max_y": 1974
        },
        {
          "line": 15,
          "min_x": 867,
          "max_x": 973,
          "min_y": 1892,
          "max_y": 1980
        },
        {
          "line": 15,
          "min_x": 730,
          "max_x": 860,
          "min_y": 1891,
          "max_y": 1964
        },
        {
          "line": 15,
          "min_x": 737,
          "max_x": 726,
          "min_y": 1872,
          "max_y": 1896
        },
        {
          "line": 15,
          "min_x": 625,
          "max_x": 722,
          "min_y": 1898,
          "max_y": 1979
        },
        {
          "line": 15,
          "min_x": 508,
          "max_x": 618,
          "min_y": 1892,
          "max_y": 1997
        },
        {
          "line": 15,
          "min_x": 422,
          "max_x": 502,
          "min_y": 1898,
          "max_y": 1997
        },
        {
          "line": 15,
          "min_x": 379,
          "max_x": 421,
          "min_y": 1892,
          "max_y": 1967
        },
        {
          "line": 15,
          "min_x": 168,
          "max_x": 376,
          "min_y": 1900,
          "max_y": 1981
        },
        {
          "line": 15,
          "min_x": 64,
          "max_x": 167,
          "min_y": 1891,
          "max_y": 1986
        }
      ]
    }
  ]
}