{
  "page": 49,
  "verses": [
    {
      "sura": 2,
      "ayah": 283,
      "glyphs": [
        {
          "line": 1,
          "min_x": 1126,
          "max_x": 1196,
          "min_y": 67,
          "max_y": 139
        },
        {
          "line": 1,
          "min_x": 1039,
          "max_x": 1117,
          "min_y": 72,
          "max_y": 143
        },
        {
          "line": 1,
          "min_x": 930,
          "max_x": 1032,
          "min_y": 55,
          "max_y": 134
        },
        {
          "line": 1,
          "min_x": 860,
          "max_x": 931,
          "min_y": 60,
          "max_y": 135
        },
        {
          "line": 1,
          "min_x": 748,
          "max_x": 854,
          "min_y": 64,
          "max_y": 163
        },
        {
          "line": 1,
          "min_x": 671,
          "max_x": 748,
          "min_y": 55,
          "max_y": 151
        },
        {
          "line": 1,
          "min_x": 515,
          "max_x": 663,
          "min_y": 59,
          "max_y": 147
        },
        {
          "line": 1,
          "min_x": 408,
          "max_x": 501,
          "min_y": 58,
          "max_y": 145
        },
        {
          "line": 1,
          "min_x": 284,
          "max_x": 404,
          "min_y": 58,
          "max_y": 152
        },
        {
          "line": 1,
          "min_x": 80,
          "max_x": 279,
          "min_y": 57,
          "max_y": 139
        },
        {
          "line": 1,
          "min_x": 76,
          "max_x": 78,
          "min_y": 30,
          "max_y": 55
        },
        {
          "line": 2,
          "min_x": 1127,
          "max_x": 1195,
          "min_y": 194,
          "max_y": 281
        },
        {
          "line": 2,
          "min_x": 1043,
          "max_x": 1119,
          "min_y": 186,
          "max_y": 275
        },
        {
          "line": 2,
          "min_x": 867,
          "max_x": 1033,
          "min_y": 181,
          "max_y": 288
        },
        {
          "line": 2,
          "min_x": 725,
          "max_x": 858,
          "min_y": 198,
          "max_y": 267
        },
        {
          "line": 2,
          "min_x": 599,
          "max_x": 716,
          "min_y": 192,
          "max_y": 273
        },
        {
          "line": 2,
          "min_x": 494,
          "max_x": 599,
          "min_y": 180,
          "max_y": 275
        },
        {
          "line": 2,
          "min_x": 352,
          "max_x": 483,
          "min_y": 193,
          "max_y": 276
        },
        {
          "line": 2,
          "min_x": 208,
          "max_x": 346,
          "min_y": 189,
          "max_y": 257
        },
        {
          "line": 2,
          "min_x": 76,
          "max_x": 203,
          "min_y": 190,
          "max_y": 285
        },
        {
          "line": 3,
          "min_x": 1128,
          "max_x": 1193,
          "min_y": 328,
          "max_y": 390
        },
        {
          "line": 3,
          "min_x": 1037,
          "max_x": 1125,
          "min_y": 324,
          "max_y": 403
        },
        {
          "line": 3,
          "min_x": 1038,
          "max_x": 1034,
          "min_y": 295,
          "max_y": 321
        },
        {
          "line": 3,
          "min_x": 955,
          "max_x": 1030,
          "min_y": 324,
          "max_y": 400
        },
        {
          "line": 3,
          "min_x": 784,
          "max_x": 948,
          "min_y": 321,
          "max_y": 405
        },
        {
          "line": 3,
          "min_x": 559,
          "max_x": 770,
          "min_y": 317,
          "max_y": 404
        },
        {
          "line": 3,
          "min_x": 557,
          "max_x": 545,
          "min_y": 297,
          "max_y": 321
        },
        {
          "line": 3,
          "min_x": 452,
          "max_x": 541,
          "min_y": 327,
          "max_y": 402
        },
        {
          "line": 3,
          "min_x": 220,
          "max_x": 440,
          "min_y": 323,
          "max_y": 405
        },
        {
          "line": 3,
          "min_x": 77,
          "max_x": 210,
          "min_y": 322,
          "max_y": 414
        },
        {
          "line": 4,
          "min_x": 1092,
          "max_x": 1197,
          "min_y": 456,
          "max_y": 552
        },
        {
          "line": 4,
          "min_x": 980,
          "max_x": 1091,
          "min_y": 455,
          "max_y": 535
        },
        {
          "line": 4,
          "min_x": 990,
          "max_x": 977,
          "min_y": 434,
          "max_y": 460
        },
        {
          "line": 4,
          "min_x": 875,
          "max_x": 973,
          "min_y": 459,
          "max_y": 533
        },
        {
          "line": 4,
          "min_x": 799,
          "max_x": 875,
          "min_y": 464,
          "max_y": 545
        },
        {
          "line": 4,
          "min_x": 630,
          "max_x": 794,
          "min_y": 453,
          "max_y": 535
        },
        {
          "line": 4,
          "min_x": 503,
          "max_x": 625,
          "min_y": 463,
          "max_y": 548
        },
        {
          "line": 4,
          "min_x": 400,
          "max_x": 502,
          "min_y": 449,
          "max_y": 544
        }
      ]
    },
    {
      "sura": 2,
      "ayah": 284,
      "glyphs": [
        {
          "line": 4,
          "min_x": 339,
          "max_x": 401,
          "min_y": 464,
          "max_y": 538
        },
        {
          "line": 4,
          "min_x": 296,
          "max_x": 337,
          "min_y": 468,
          "max_y": 522
        },
        {
          "line": 4,
          "min_x": 251,
          "max_x": 293,
          "min_y": 475,
          "max_y": 545
        },
        {
          "line": 4,
          "min_x": 74,
          "max_x": 247,
          "min_y": 463,
          "max_y": 541
        },
        {
          "line": 5,
          "min_x": 1122,
          "max_x": 1196,
          "min_y": 596,
          "max_y": 668
        },
        {
          "line": 5,
          "min_x": 1071,
          "max_x": 1116,
          "min_y": 607,
          "max_y": 676
        },
        {
          "line": 5,
          "min_x": 911,
          "max_x": 1056,
          "min_y": 584,
          "max_y": 672
        },
        {
          "line": 5,
          "min_x": 904,
          "max_x": 897,
          "min_y": 588,
          "max_y": 612
        },
        {
          "line": 5,
          "min_x": 809,
          "max_x": 893,
          "min_y": 597,
          "max_y": 677
        },
        {
          "line": 5,
          "min_x": 676,
          "max_x": 801,
          "min_y": 587,
          "max_y": 668
        },
        {
          "line": 5,
          "min_x": 625,
          "max_x": 666,
          "min_y": 589,
          "max_y": 656
        },
        {
          "line": 5,
          "min_x": 564,
          "max_x": 617,
          "min_y": 608,
          "max_y": 676
        },
        {
          "line": 5,
          "min_x": 317,
          "max_x": 562,
          "min_y": 584,
          "max_y": 689
        },
        {
          "line": 5,
          "min_x": 251,
          "max_x": 304,
          "min_y": 585,
          "max_y": 667
        },
        {
          "line": 5,
          "min_x": 74,
          "max_x": 250,
          "min_y": 584,
          "max_y": 669
        },
        {
          "line": 6,
          "min_x": 970,
          "max_x": 1195,
          "min_y": 716,
          "max_y": 820
        },
        {
          "line": 6,
          "min_x": 918,
          "max_x": 960,
          "min_y": 758,
          "max_y": 812
        },
        {
          "line": 6,
          "min_x": 843,
          "max_x": 915,
          "min_y": 725,
          "max_y": 790
        },
        {
          "line": 6,
          "min_x": 835,
          "max_x": 839,
          "min_y": 708,
          "max_y": 734
        },
        {
          "line": 6,
          "min_x": 681,
          "max_x": 835,
          "min_y": 726,
          "max_y": 808
        },
        {
          "line": 6,
          "min_x": 593,
          "max_x": 679,
          "min_y": 734,
          "max_y": 803
        },
        {
          "line": 6,
          "min_x": 475,
          "max_x": 586,
          "min_y": 727,
          "max_y": 803
        },
        {
          "line": 6,
          "min_x": 296,
          "max_x": 472,
          "min_y": 726,
          "max_y": 804
        },
        {
          "line": 6,
          "min_x": 225,
          "max_x": 288,
          "min_y": 731,
          "max_y": 801
        },
        {
          "line": 6,
          "min_x": 82,
          "max_x": 216,
          "min_y": 728,
          "max_y": 805
        },
        {
          "line": 6,
          "min_x": 74,
          "max_x": 77,
          "min_y": 709,
          "max_y": 735
        },
        {
          "line": 7,
          "min_x": 1096,
          "max_x": 1192,
          "min_y": 857,
          "max_y": 931
        },
        {
          "line": 7,
          "min_x": 1023,
          "max_x": 1093,
          "min_y": 856,
          "max_y": 935
        },
        {
          "line": 7,
          "min_x": 882,
          "max_x": 1024,
          "min_y": 857,
          "max_y": 948
        },
        {
          "line": 7,
          "min_x": 784,
          "max_x": 882,
          "min_y": 858,
          "max_y": 944
        },
        {
          "line": 7,
          "min_x": 659,
          "max_x": 782,
          "min_y": 856,
          "max_y": 944
        },
        {
          "line": 7,
          "min_x": 551,
          "max_x": 649,
          "min_y": 848,
          "max_y": 943
        }
      ]
    },
    {
      "sura": 2,
      "ayah": 285,
      "glyphs": [
        {
          "line": 7,
          "min_x": 441,
          "max_x": 552,
          "min_y": 866,
          "max_y": 933
        },
        {
          "line": 7,
          "min_x": 285,
          "max_x": 434,
          "min_y": 850,
          "max_y": 938
        },
        {
          "line": 7,
          "min_x": 192,
          "max_x": 277,
          "min_y": 860,
          "max_y": 947
        },
        {
          "line": 7,
          "min_x": 78,
          "max_x": 188,
          "min_y": 844,
          "max_y": 950
        },
        {
          "line": 8,
          "min_x": 1108,
          "max_x": 1195,
          "min_y": 987,
          "max_y": 1074
        },
        {
          "line": 8,
          "min_x": 1044,
          "max_x": 1102,
          "min_y": 1025,
          "max_y": 1071
        },
        {
          "line": 8,
          "min_x": 929,
          "max_x": 1037,
          "min_y": 989,
          "max_y": 1082
        },
        {
          "line": 8,
          "min_x": 703,
          "max_x": 920,
          "min_y": 986,
          "max_y": 1070
        },
        {
          "line": 8,
          "min_x": 705,
          "max_x": 683,
          "min_y": 969,
          "max_y": 994
        },
        {
          "line": 8,
          "min_x": 624,
          "max_x": 679,
          "min_y": 964,
          "max_y": 1069
        },
        {
          "line": 8,
          "min_x": 512,
          "max_x": 619,
          "min_y": 997,
          "max_y": 1069
        },
        {
          "line": 8,
          "min_x": 421,
          "max_x": 506,
          "min_y": 988,
          "max_y": 1082
        },
        {
          "line": 8,
          "min_x": 201,
          "max_x": 416,
          "min_y": 981,
          "max_y": 1079
        },
        {
          "line": 8,
          "min_x": 75,
          "max_x": 195,
          "min_y": 978,
          "max_y": 1078
        },
        {
          "line": 9,
          "min_x": 1025,
          "max_x": 1195,
          "min_y": 1127,
          "max_y": 1209
        },
        {
          "line": 9,
          "min_x": 972,
          "max_x": 1015,
          "min_y": 1124,
          "max_y": 1192
        },
        {
          "line": 9,
          "min_x": 869,
          "max_x": 969,
          "min_y": 1119,
          "max_y": 1219
        },
        {
          "line": 9,
          "min_x": 739,
          "max_x": 861,
          "min_y": 1126,
          "max_y": 1201
        },
        {
          "line": 9,
          "min_x": 633,
          "max_x": 732,
          "min_y": 1119,
          "max_y": 1213
        },
        {
          "line": 9,
          "min_x": 573,
          "max_x": 631,
          "min_y": 1132,
          "max_y": 1201
        },
        {
          "line": 9,
          "min_x": 403,
          "max_x": 564,
          "min_y": 1119,
          "max_y": 1209
        },
        {
          "line": 9,
          "min_x": 405,
          "max_x": 395,
          "min_y": 1127,
          "max_y": 1152
        },
        {
          "line": 9,
          "min_x": 228,
          "max_x": 391,
          "min_y": 1117,
          "max_y": 1199
        },
        {
          "line": 9,
          "min_x": 74,
          "max_x": 221,
          "min_y": 1130,
          "max_y": 1205
        },
        {
          "line": 10,
          "min_x": 1041,
          "max_x": 1195,
          "min_y": 1249,
          "max_y": 1331
        },
        {
          "line": 10,
          "min_x": 1027,
          "max_x": 1037,
          "min_y": 1234,
          "max_y": 1260
        },
        {
          "line": 10,
          "min_x": 832,
          "max_x": 1033,
          "min_y": 1252,
          "max_y": 1337
        },
        {
          "line": 10,
          "min_x": 737,
          "max_x": 825,
          "min_y": 1258,
          "max_y": 1335
        },
        {
          "line": 10,
          "min_x": 566,
          "max_x": 730,
          "min_y": 1252,
          "max_y": 1342
        },
        {
          "line": 10,
          "min_x": 406,
          "max_x": 564,
          "min_y": 1258,
          "max_y": 1341
        },
        {
          "line": 10,
          "min_x": 297,
          "max_x": 399,
          "min_y": 1247,
          "max_y": 1342
        }
      ]
    },
    {
      "sura": 2,
      "ayah": 286,
      "glyphs": [
        {
          "line": 10,
          "min_x": 245,
          "max_x": 298,
          "min_y": 1255,
          "max_y": 1322
        },
        {
          "line": 10,
          "min_x": 75,
          "max_x": 241,
          "min_y": 1253,
          "max_y": 1341
        },
        {
          "line": 11,
          "min_x": 1123,
          "max_x": 1196,
          "min_y": 1392,
          "max_y": 1455
        },
        {
          "line": 11,
          "min_x": 1004,
          "max_x": 1119,
          "min_y": 1388,
          "max_y": 1454
        },
        {
          "line": 11,
          "min_x": 933,
          "max_x": 994,
          "min_y": 1378,
          "max_y": 1472
        },
        {
          "line": 11,
          "min_x": 757,
          "max_x": 923,
          "min_y": 1391,
          "max_y": 1468
        },
        {
          "line": 11,
          "min_x": 752,
          "max_x": 743,
          "min_y": 1380,
          "max_y": 1404
        },
        {
          "line": 11,
          "min_x": 667,
          "max_x": 739,
          "min_y": 1389,
          "max_y": 1467
        },
        {
          "line": 11,
          "min_x": 620,
          "max_x": 660,
          "min_y": 1396,
          "max_y": 1453
        },
        {
          "line": 11,
          "min_x": 463,
          "max_x": 620,
          "min_y": 1388,
          "max_y": 1465
        },
        {
          "line": 11,
          "min_x": 321,
          "max_x": 453,
          "min_y": 1392,
          "max_y": 1473
        },
        {
          "line": 11,
          "min_x": 274,
          "max_x": 313,
          "min_y": 1399,
          "max_y": 1454
        },
        {
          "line": 11,
          "min_x": 87,
          "max_x": 265,
          "min_y": 1389,
          "max_y": 1465
        },
        {
          "line": 11,
          "min_x": 75,
          "max_x": 77,
          "min_y": 1365,
          "max_y": 1391
        },
        {
          "line": 12,
          "min_x": 1110,
          "max_x": 1197,
          "min_y": 1525,
          "max_y": 1604
        },
        {
          "line": 12,
          "min_x": 1054,
          "max_x": 1097,
          "min_y": 1523,
          "max_y": 1591
        },
        {
          "line": 12,
          "min_x": 848,
          "max_x": 1046,
          "min_y": 1520,
          "max_y": 1603
        },
        {
          "line": 12,
          "min_x": 798,
          "max_x": 847,
          "min_y": 1542,
          "max_y": 1610
        },
        {
          "line": 12,
          "min_x": 641,
          "max_x": 789,
          "min_y": 1518,
          "max_y": 1605
        },
        {
          "line": 12,
          "min_x": 591,
          "max_x": 638,
          "min_y": 1516,
          "max_y": 1598
        },
        {
          "line": 12,
          "min_x": 422,
          "max_x": 586,
          "min_y": 1514,
          "max_y": 1590
        },
        {
          "line": 12,
          "min_x": 411,
          "max_x": 413,
          "min_y": 1494,
          "max_y": 1518
        },
        {
          "line": 12,
          "min_x": 302,
          "max_x": 409,
          "min_y": 1522,
          "max_y": 1598
        },
        {
          "line": 12,
          "min_x": 217,
          "max_x": 293,
          "min_y": 1522,
          "max_y": 1598
        },
        {
          "line": 12,
          "min_x": 74,
          "max_x": 214,
          "min_y": 1523,
          "max_y": 1603
        },
        {
          "line": 13,
          "min_x": 1053,
          "max_x": 1197,
          "min_y": 1657,
          "max_y": 1734
        },
        {
          "line": 13,
          "min_x": 935,
          "max_x": 1053,
          "min_y": 1659,
          "max_y": 1739
        },
        {
          "line": 13,
          "min_x": 849,
          "max_x": 917,
          "min_y": 1652,
          "max_y": 1721
        },
        {
          "line": 13,
          "min_x": 658,
          "max_x": 838,
          "min_y": 1656,
          "max_y": 1722
        },
        {
          "line": 13,
          "min_x": 588,
          "max_x": 658,
          "min_y": 1657,
          "max_y": 1734
        },
        {
          "line": 13,
          "min_x": 415,
          "max_x": 583,
          "min_y": 1644,
          "max_y": 1739
        },
        {
          "line": 13,
          "min_x": 347,
          "max_x": 409,
          "min_y": 1688,
          "max_y": 1733
        },
        {
          "line": 13,
          "min_x": 237,
          "max_x": 340,
          "min_y": 1650,
          "max_y": 1737
        },
        {
          "line": 13,
          "min_x": 232,
          "max_x": 234,
          "min_y": 1635,
          "max_y": 1659
        },
        {
          "line": 13,
          "min_x": 154,
          "max_x": 230,
          "min_y": 1653,
          "max_y": 1736
        },
        {
          "line": 13,
          "min_x": 75,
          "max_x": 149,
          "min_y": 1650,
          "max_y": 1729
        },
        {
          "line": 14,
          "min_x": 1033,
          "max_x": 1199,
          "min_y": 1785,
          "max_y": 1869
        },
        {
          "line": 14,
          "min_x": 987,
          "max_x": 1027,
          "min_y": 1792,
          "max_y": 1853
        },
        {
          "line": 14,
          "min_x": 936,
          "max_x": 977,
          "min_y": 1789,
          "max_y": 1855
        },
        {
          "line": 14,
          "min_x": 803,
          "max_x": 937,
          "min_y": 1785,
          "max_y": 1853
        },
        {
          "line": 14,
          "min_x": 744,
          "max_x": 796,
          "min_y": 1789,
          "max_y": 1854
        },
        {
          "line": 14,
          "min_x": 675,
          "max_x": 739,
          "min_y": 1820,
          "max_y": 1875
        },
        {
          "line": 14,
          "min_x": 670,
          "max_x": 664,
          "min_y": 1783,
          "max_y": 1808
        },
        {
          "line": 14,
          "min_x": 521,
          "max_x": 660,
          "min_y": 1787,
          "max_y": 1863
        },
        {
          "line": 14,
          "min_x": 439,
          "max_x": 516,
          "min_y": 1783,
          "max_y": 1855
        },
        {
          "line": 14,
          "min_x": 295,
          "max_x": 432,
          "min_y": 1788,
          "max_y": 1879
        },
        {
          "line": 14,
          "min_x": 256,
          "max_x": 296,
          "min_y": 1783,
          "max_y": 1853
        },
        {
          "line": 14,
          "min_x": 77,
          "max_x": 248,
          "min_y": 1785,
          "max_y": 1862
        },
        {
          "line": 14,
          "min_x": 78,
          "max_x": 76,
          "min_y": 1767,
          "max_y": 1791
        },
        {
          "line": 15,
          "min_x": 1084,
          "max_x": 1192,
          "min_y": 1917,
          "max_y": 1989
        },
        {
          "line": 15,
          "min_x": 923,
          "max_x": 1081,
          "min_y": 1920,
          "max_y": 1999
        },
        {
          "line": 15,
          "min_x": 729,
          "max_x": 912,
          "min_y": 1918,
          "max_y": 1998
        },
        {
          "line": 15,
          "min_x": 650,
          "max_x": 723,
          "min_y": 1922,
          "max_y": 1998
        },
        {
          "line": 15,
          "min_x": 513,
          "max_x": 643,
          "min_y": 1920,
          "max_y": 2008
        },
        {
          "line": 15,
          "min_x": 193,
          "max_x": 508,
          "min_y": 1920,
          "max_y": 2013
        },
        {
          "line": 15,
          "min_x": 73,
          "max_x": 175,
          "min_y": 1912,
          "max_y": 2007
        }
      ]
    }
  ]
}