{
  "page": 448,
  "verses": [
    {
      "sura": 37,
      "ayah": 52,
      "glyphs": [
        {
          "line": 1,
          "min_x": 1119,
          "max_x": 1212,
          "min_y": 36,
          "max_y": 122
        },
        {
          "line": 1,
          "min_x": 1009,
          "max_x": 1111,
          "min_y": 36,
          "max_y": 114
        },
        {
          "line": 1,
          "min_x": 924,
          "max_x": 998,
          "min_y": 43,
          "max_y": 123
        },
        {
          "line": 1,
          "min_x": 726,
          "max_x": 920,
          "min_y": 42,
          "max_y": 124
        },
        {
          "line": 1,
          "min_x": 615,
          "max_x": 717,
          "min_y": 32,
          "max_y": 127
        }
      ]
    },
    {
      "sura": 37,
      "ayah": 53,
      "glyphs": [
        {
          "line": 1,
          "min_x": 534,
          "max_x": 616,
          "min_y": 36,
          "max_y": 112
        },
        {
          "line": 1,
          "min_x": 450,
          "max_x": 524,
          "min_y": 46,
          "max_y": 119
        },
        {
          "line": 1,
          "min_x": 364,
          "max_x": 442,
          "min_y": 30,
          "max_y": 119
        },
        {
          "line": 1,
          "min_x": 280,
          "max_x": 356,
          "min_y": 36,
          "max_y": 122
        },
        {
          "line": 1,
          "min_x": 131,
          "max_x": 275,
          "min_y": 42,
          "max_y": 119
        },
        {
          "line": 1,
          "min_x": 60,
          "max_x": 123,
          "min_y": 37,
          "max_y": 117
        },
        {
          "line": 2,
          "min_x": 1056,
          "max_x": 1211,
          "min_y": 175,
          "max_y": 261
        },
        {
          "line": 2,
          "min_x": 948,
          "max_x": 1050,
          "min_y": 165,
          "max_y": 260
        }
      ]
    },
    {
      "sura": 37,
      "ayah": 54,
      "glyphs": [
        {
          "line": 2,
          "min_x": 874,
          "max_x": 949,
          "min_y": 174,
          "max_y": 244
        },
        {
          "line": 2,
          "min_x": 795,
          "max_x": 868,
          "min_y": 177,
          "max_y": 250
        },
        {
          "line": 2,
          "min_x": 704,
          "max_x": 791,
          "min_y": 165,
          "max_y": 246
        },
        {
          "line": 2,
          "min_x": 548,
          "max_x": 704,
          "min_y": 167,
          "max_y": 256
        },
        {
          "line": 2,
          "min_x": 437,
          "max_x": 539,
          "min_y": 165,
          "max_y": 260
        }
      ]
    },
    {
      "sura": 37,
      "ayah": 55,
      "glyphs": [
        {
          "line": 2,
          "min_x": 309,
          "max_x": 438,
          "min_y": 166,
          "max_y": 273
        },
        {
          "line": 2,
          "min_x": 212,
          "max_x": 309,
          "min_y": 178,
          "max_y": 256
        },
        {
          "line": 2,
          "min_x": 166,
          "max_x": 212,
          "min_y": 189,
          "max_y": 255
        },
        {
          "line": 2,
          "min_x": 61,
          "max_x": 156,
          "min_y": 177,
          "max_y": 254
        },
        {
          "line": 3,
          "min_x": 1046,
          "max_x": 1208,
          "min_y": 305,
          "max_y": 393
        },
        {
          "line": 3,
          "min_x": 937,
          "max_x": 1039,
          "min_y": 298,
          "max_y": 392
        }
      ]
    },
    {
      "sura": 37,
      "ayah": 56,
      "glyphs": [
        {
          "line": 3,
          "min_x": 860,
          "max_x": 938,
          "min_y": 305,
          "max_y": 377
        },
        {
          "line": 3,
          "min_x": 766,
          "max_x": 852,
          "min_y": 304,
          "max_y": 387
        },
        {
          "line": 3,
          "min_x": 718,
          "max_x": 763,
          "min_y": 322,
          "max_y": 391
        },
        {
          "line": 3,
          "min_x": 604,
          "max_x": 710,
          "min_y": 300,
          "max_y": 387
        },
        {
          "line": 3,
          "min_x": 476,
          "max_x": 597,
          "min_y": 297,
          "max_y": 395
        },
        {
          "line": 3,
          "min_x": 362,
          "max_x": 464,
          "min_y": 298,
          "max_y": 393
        }
      ]
    },
    {
      "sura": 37,
      "ayah": 57,
      "glyphs": [
        {
          "line": 3,
          "min_x": 245,
          "max_x": 363,
          "min_y": 304,
          "max_y": 389
        },
        {
          "line": 3,
          "min_x": 139,
          "max_x": 242,
          "min_y": 301,
          "max_y": 386
        },
        {
          "line": 3,
          "min_x": 62,
          "max_x": 133,
          "min_y": 318,
          "max_y": 407
        },
        {
          "line": 4,
          "min_x": 1079,
          "max_x": 1209,
          "min_y": 432,
          "max_y": 507
        },
        {
          "line": 4,
          "min_x": 1010,
          "max_x": 1069,
          "min_y": 449,
          "max_y": 524
        },
        {
          "line": 4,
          "min_x": 787,
          "max_x": 1005,
          "min_y": 439,
          "max_y": 534
        },
        {
          "line": 4,
          "min_x": 675,
          "max_x": 776,
          "min_y": 431,
          "max_y": 526
        }
      ]
    },
    {
      "sura": 37,
      "ayah": 58,
      "glyphs": [
        {
          "line": 4,
          "min_x": 599,
          "max_x": 676,
          "min_y": 432,
          "max_y": 505
        },
        {
          "line": 4,
          "min_x": 513,
          "max_x": 590,
          "min_y": 439,
          "max_y": 518
        },
        {
          "line": 4,
          "min_x": 367,
          "max_x": 508,
          "min_y": 445,
          "max_y": 531
        },
        {
          "line": 4,
          "min_x": 252,
          "max_x": 353,
          "min_y": 431,
          "max_y": 526
        }
      ]
    },
    {
      "sura": 37,
      "ayah": 59,
      "glyphs": [
        {
          "line": 4,
          "min_x": 181,
          "max_x": 253,
          "min_y": 430,
          "max_y": 526
        },
        {
          "line": 4,
          "min_x": 61,
          "max_x": 177,
          "min_y": 440,
          "max_y": 521
        },
        {
          "line": 5,
          "min_x": 1081,
          "max_x": 1208,
          "min_y": 556,
          "max_y": 650
        },
        {
          "line": 5,
          "min_x": 1010,
          "max_x": 1075,
          "min_y": 577,
          "max_y": 649
        },
        {
          "line": 5,
          "min_x": 925,
          "max_x": 1006,
          "min_y": 569,
          "max_y": 652
        },
        {
          "line": 5,
          "min_x": 740,
          "max_x": 921,
          "min_y": 562,
          "max_y": 665
        },
        {
          "line": 5,
          "min_x": 627,
          "max_x": 729,
          "min_y": 564,
          "max_y": 658
        }
      ]
    },
    {
      "sura": 37,
      "ayah": 60,
      "glyphs": [
        {
          "line": 5,
          "min_x": 564,
          "max_x": 628,
          "min_y": 573,
          "max_y": 664
        },
        {
          "line": 5,
          "min_x": 461,
          "max_x": 559,
          "min_y": 570,
          "max_y": 638
        },
        {
          "line": 5,
          "min_x": 388,
          "max_x": 459,
          "min_y": 563,
          "max_y": 653
        },
        {
          "line": 5,
          "min_x": 287,
          "max_x": 389,
          "min_y": 566,
          "max_y": 653
        },
        {
          "line": 5,
          "min_x": 175,
          "max_x": 288,
          "min_y": 571,
          "max_y": 678
        },
        {
          "line": 5,
          "min_x": 63,
          "max_x": 165,
          "min_y": 564,
          "max_y": 659
        }
      ]
    },
    {
      "sura": 37,
      "ayah": 61,
      "glyphs": [
        {
          "line": 6,
          "min_x": 1107,
          "max_x": 1209,
          "min_y": 712,
          "max_y": 796
        },
        {
          "line": 6,
          "min_x": 1018,
          "max_x": 1104,
          "min_y": 705,
          "max_y": 773
        },
        {
          "line": 6,
          "min_x": 855,
          "max_x": 1011,
          "min_y": 704,
          "max_y": 801
        },
        {
          "line": 6,
          "min_x": 675,
          "max_x": 851,
          "min_y": 701,
          "max_y": 789
        },
        {
          "line": 6,
          "min_x": 560,
          "max_x": 662,
          "min_y": 697,
          "max_y": 792
        }
      ]
    },
    {
      "sura": 37,
      "ayah": 62,
      "glyphs": [
        {
          "line": 6,
          "min_x": 446,
          "max_x": 561,
          "min_y": 696,
          "max_y": 786
        },
        {
          "line": 6,
          "min_x": 357,
          "max_x": 443,
          "min_y": 701,
          "max_y": 785
        },
        {
          "line": 6,
          "min_x": 273,
          "max_x": 357,
          "min_y": 688,
          "max_y": 782
        },
        {
          "line": 6,
          "min_x": 222,
          "max_x": 262,
          "min_y": 699,
          "max_y": 801
        },
        {
          "line": 6,
          "min_x": 63,
          "max_x": 211,
          "min_y": 700,
          "max_y": 782
        },
        {
          "line": 7,
          "min_x": 1094,
          "max_x": 1211,
          "min_y": 822,
          "max_y": 936
        },
        {
          "line": 7,
          "min_x": 984,
          "max_x": 1085,
          "min_y": 830,
          "max_y": 925
        }
      ]
    },
    {
      "sura": 37,
      "ayah": 63,
      "glyphs": [
        {
          "line": 7,
          "min_x": 926,
          "max_x": 985,
          "min_y": 838,
          "max_y": 924
        },
        {
          "line": 7,
          "min_x": 760,
          "max_x": 926,
          "min_y": 840,
          "max_y": 918
        },
        {
          "line": 7,
          "min_x": 655,
          "max_x": 758,
          "min_y": 831,
          "max_y": 917
        },
        {
          "line": 7,
          "min_x": 465,
          "max_x": 645,
          "min_y": 832,
          "max_y": 924
        },
        {
          "line": 7,
          "min_x": 349,
          "max_x": 451,
          "min_y": 830,
          "max_y": 925
        }
      ]
    },
    {
      "sura": 37,
      "ayah": 64,
      "glyphs": [
        {
          "line": 7,
          "min_x": 247,
          "max_x": 350,
          "min_y": 840,
          "max_y": 928
        },
        {
          "line": 7,
          "min_x": 59,
          "max_x": 240,
          "min_y": 832,
          "max_y": 919
        },
        {
          "line": 8,
          "min_x": 1103,
          "max_x": 1208,
          "min_y": 967,
          "max_y": 1072
        },
        {
          "line": 8,
          "min_x": 1045,
          "max_x": 1095,
          "min_y": 988,
          "max_y": 1056
        },
        {
          "line": 8,
          "min_x": 939,
          "max_x": 1042,
          "min_y": 962,
          "max_y": 1064
        },
        {
          "line": 8,
          "min_x": 762,
          "max_x": 931,
          "min_y": 967,
          "max_y": 1061
        },
        {
          "line": 8,
          "min_x": 648,
          "max_x": 750,
          "min_y": 963,
          "max_y": 1058
        }
      ]
    },
    {
      "sura": 37,
      "ayah": 65,
      "glyphs": [
        {
          "line": 8,
          "min_x": 500,
          "max_x": 649,
          "min_y": 968,
          "max_y": 1051
        },
        {
          "line": 8,
          "min_x": 387,
          "max_x": 484,
          "min_y": 955,
          "max_y": 1037
        },
        {
          "line": 8,
          "min_x": 249,
          "max_x": 384,
          "min_y": 977,
          "max_y": 1052
        },
        {
          "line": 8,
          "min_x": 61,
          "max_x": 242,
          "min_y": 966,
          "max_y": 1061
        },
        {
          "line": 9,
          "min_x": 1111,
          "max_x": 1213,
          "min_y": 1096,
          "max_y": 1191
        }
      ]
    },
    {
      "sura": 37,
      "ayah": 66,
      "glyphs": [
        {
          "line": 9,
          "min_x": 1003,
          "max_x": 1112,
          "min_y": 1109,
          "max_y": 1203
        },
        {
          "line": 9,
          "min_x": 862,
          "max_x": 1002,
          "min_y": 1100,
          "max_y": 1186
        },
        {
          "line": 9,
          "min_x": 782,
          "max_x": 857,
          "min_y": 1114,
          "max_y": 1188
        },
        {
          "line": 9,
          "min_x": 632,
          "max_x": 777,
          "min_y": 1111,
          "max_y": 1190
        },
        {
          "line": 9,
          "min_x": 551,
          "max_x": 626,
          "min_y": 1115,
          "max_y": 1191
        },
        {
          "line": 9,
          "min_x": 393,
          "max_x": 542,
          "min_y": 1102,
          "max_y": 1186
        },
        {
          "line": 9,
          "min_x": 279,
          "max_x": 381,
          "min_y": 1096,
          "max_y": 1191
        }
      ]
    },
    {
      "sura": 37,
      "ayah": 67,
      "glyphs": [
        {
          "line": 9,
          "min_x": 225,
          "max_x": 280,
          "min_y": 1094,
          "max_y": 1205
        },
        {
          "line": 9,
          "min_x": 166,
          "max_x": 217,
          "min_y": 1106,
          "max_y": 1188
        },
        {
          "line": 9,
          "min_x": 61,
          "max_x": 159,
          "min_y": 1101,
          "max_y": 1183
        },
        {
          "line": 10,
          "min_x": 1119,
          "max_x": 1215,
          "min_y": 1241,
          "max_y": 1322
        },
        {
          "line": 10,
          "min_x": 999,
          "max_x": 1107,
          "min_y": 1237,
          "max_y": 1321
        },
        {
          "line": 10,
          "min_x": 934,
          "max_x": 994,
          "min_y": 1249,
          "max_y": 1321
        },
        {
          "line": 10,
          "min_x": 811,
          "max_x": 933,
          "min_y": 1245,
          "max_y": 1334
        },
        {
          "line": 10,
          "min_x": 699,
          "max_x": 801,
          "min_y": 1229,
          "max_y": 1323
        }
      ]
    },
    {
      "sura": 37,
      "ayah": 68,
      "glyphs": [
        {
          "line": 10,
          "min_x": 644,
          "max_x": 700,
          "min_y": 1225,
          "max_y": 1340
        },
        {
          "line": 10,
          "min_x": 589,
          "max_x": 636,
          "min_y": 1241,
          "max_y": 1327
        },
        {
          "line": 10,
          "min_x": 400,
          "max_x": 583,
          "min_y": 1241,
          "max_y": 1342
        },
        {
          "line": 10,
          "min_x": 307,
          "max_x": 399,
          "min_y": 1235,
          "max_y": 1327
        },
        {
          "line": 10,
          "min_x": 168,
          "max_x": 304,
          "min_y": 1228,
          "max_y": 1341
        },
        {
          "line": 10,
          "min_x": 60,
          "max_x": 163,
          "min_y": 1229,
          "max_y": 1324
        }
      ]
    },
    {
      "sura": 37,
      "ayah": 69,
      "glyphs": [
        {
          "line": 11,
          "min_x": 1123,
          "max_x": 1209,
          "min_y": 1375,
          "max_y": 1468
        },
        {
          "line": 11,
          "min_x": 1022,
          "max_x": 1115,
          "min_y": 1367,
          "max_y": 1452
        },
        {
          "line": 11,
          "min_x": 856,
          "max_x": 1018,
          "min_y": 1369,
          "max_y": 1446
        },
        {
          "line": 11,
          "min_x": 726,
          "max_x": 856,
          "min_y": 1369,
          "max_y": 1456
        },
        {
          "line": 11,
          "min_x": 614,
          "max_x": 716,
          "min_y": 1362,
          "max_y": 1457
        }
      ]
    },
    {
      "sura": 37,
      "ayah": 70,
      "glyphs": [
        {
          "line": 11,
          "min_x": 518,
          "max_x": 615,
          "min_y": 1372,
          "max_y": 1472
        },
        {
          "line": 11,
          "min_x": 443,
          "max_x": 517,
          "min_y": 1365,
          "max_y": 1450
        },
        {
          "line": 11,
          "min_x": 319,
          "max_x": 441,
          "min_y": 1377,
          "max_y": 1484
        },
        {
          "line": 11,
          "min_x": 172,
          "max_x": 314,
          "min_y": 1377,
          "max_y": 1461
        },
        {
          "line": 11,
          "min_x": 62,
          "max_x": 164,
          "min_y": 1362,
          "max_y": 1457
        }
      ]
    },
    {
      "sura": 37,
      "ayah": 71,
      "glyphs": [
        {
          "line": 12,
          "min_x": 1108,
          "max_x": 1210,
          "min_y": 1501,
          "max_y": 1581
        },
        {
          "line": 12,
          "min_x": 1008,
          "max_x": 1103,
          "min_y": 1497,
          "max_y": 1584
        },
        {
          "line": 12,
          "min_x": 879,
          "max_x": 1006,
          "min_y": 1497,
          "max_y": 1608
        },
        {
          "line": 12,
          "min_x": 699,
          "max_x": 870,
          "min_y": 1495,
          "max_y": 1576
        },
        {
          "line": 12,
          "min_x": 553,
          "max_x": 697,
          "min_y": 1492,
          "max_y": 1598
        },
        {
          "line": 12,
          "min_x": 430,
          "max_x": 532,
          "min_y": 1495,
          "max_y": 1590
        }
      ]
    },
    {
      "sura": 37,
      "ayah": 72,
      "glyphs": [
        {
          "line": 12,
          "min_x": 314,
          "max_x": 431,
          "min_y": 1500,
          "max_y": 1582
        },
        {
          "line": 12,
          "min_x": 160,
          "max_x": 307,
          "min_y": 1498,
          "max_y": 1580
        },
        {
          "line": 12,
          "min_x": 62,
          "max_x": 150,
          "min_y": 1523,
          "max_y": 1605
        },
        {
          "line": 13,
          "min_x": 1047,
          "max_x": 1207,
          "min_y": 1632,
          "max_y": 1729
        },
        {
          "line": 13,
          "min_x": 932,
          "max_x": 1034,
          "min_y": 1628,
          "max_y": 1723
        }
      ]
    },
    {
      "sura": 37,
      "ayah": 73,
      "glyphs": [
        {
          "line": 13,
          "min_x": 789,
          "max_x": 933,
          "min_y": 1632,
          "max_y": 1718
        },
        {
          "line": 13,
          "min_x": 611,
          "max_x": 789,
          "min_y": 1635,
          "max_y": 1718
        },
        {
          "line": 13,
          "min_x": 530,
          "max_x": 600,
          "min_y": 1633,
          "max_y": 1709
        },
        {
          "line": 13,
          "min_x": 382,
          "max_x": 522,
          "min_y": 1623,
          "max_y": 1723
        },
        {
          "line": 13,
          "min_x": 179,
          "max_x": 371,
          "min_y": 1630,
          "max_y": 1725
        },
        {
          "line": 13,
          "min_x": 63,
          "max_x": 166,
          "min_y": 1628,
          "max_y": 1722
        }
      ]
    },
    {
      "sura": 37,
      "ayah": 74,
      "glyphs": [
        {
          "line": 14,
          "min_x": 1148,
          "max_x": 1209,
          "min_y": 1756,
          "max_y": 1853
        },
        {
          "line": 14,
          "min_x": 1035,
          "max_x": 1145,
          "min_y": 1776,
          "max_y": 1846
        },
        {
          "line": 14,
          "min_x": 954,
          "max_x": 1028,
          "min_y": 1767,
          "max_y": 1850
        },
        {
          "line": 14,
          "min_x": 653,
          "max_x": 949,
          "min_y": 1766,
          "max_y": 1856
        },
        {
          "line": 14,
          "min_x": 532,
          "max_x": 633,
          "min_y": 1761,
          "max_y": 1856
        }
      ]
    },
    {
      "sura": 37,
      "ayah": 75,
      "glyphs": [
        {
          "line": 14,
          "min_x": 413,
          "max_x": 533,
          "min_y": 1764,
          "max_y": 1847
        },
        {
          "line": 14,
          "min_x": 280,
          "max_x": 405,
          "min_y": 1767,
          "max_y": 1834
        },
        {
          "line": 14,
          "min_x": 195,
          "max_x": 272,
          "min_y": 1767,
          "max_y": 1868
        },
        {
          "line": 14,
          "min_x": 61,
          "max_x": 182,
          "min_y": 1766,
          "max_y": 1872
        },
        {
          "line": 15,
          "min_x": 1003,
          "max_x": 1207,
          "min_y": 1900,
          "max_y": 1991
        },
        {
          "line": 15,
          "min_x": 889,
          "max_x": 991,
          "min_y": 1894,
          "max_y": 1989
        }
      ]
    },
    {
      "sura": 37,
      "ayah": 76,
      "glyphs": [
        {
          "line": 15,
          "min_x": 716,
          "max_x": 890,
          "min_y": 1897,
          "max_y": 1981
        },
        {
          "line": 15,
          "min_x": 572,
          "max_x": 709,
          "min_y": 1892,
          "max_y": 1982
        },
        {
          "line": 15,
          "min_x": 459,
          "max_x": 570,
          "min_y": 1912,
          "max_y": 1983
        },
        {
          "line": 15,
          "min_x": 308,
          "max_x": 453,
          "min_y": 1894,
          "max_y": 1999
        },
        {
          "line": 15,
          "min_x": 167,
          "max_x": 300,
          "min_y": 1895,
          "max_y": 2008
        },
        {
          "line": 15,
          "min_x": 64,
          "max_x": 167,
          "min_y": 1894,
          "max_y": 1989
        }
      ]
    }
  ]
}