{
  "page": 55,
  "verses": [
    {
      "sura": 3,
      "ayah": 38,
      "glyphs": [
        {
          "line": 1,
          "min_x": 1041,
          "max_x": 1202,
          "min_y": 56,
          "max_y": 138
        },
        {
          "line": 1,
          "min_x": 968,
          "max_x": 1036,
          "min_y": 59,
          "max_y": 123
        },
        {
          "line": 1,
          "min_x": 795,
          "max_x": 962,
          "min_y": 56,
          "max_y": 152
        },
        {
          "line": 1,
          "min_x": 701,
          "max_x": 787,
          "min_y": 49,
          "max_y": 132
        },
        {
          "line": 1,
          "min_x": 698,
          "max_x": 698,
          "min_y": 30,
          "max_y": 56
        },
        {
          "line": 1,
          "min_x": 626,
          "max_x": 694,
          "min_y": 55,
          "max_y": 126
        },
        {
          "line": 1,
          "min_x": 540,
          "max_x": 617,
          "min_y": 64,
          "max_y": 149
        },
        {
          "line": 1,
          "min_x": 443,
          "max_x": 530,
          "min_y": 62,
          "max_y": 133
        },
        {
          "line": 1,
          "min_x": 398,
          "max_x": 439,
          "min_y": 75,
          "max_y": 144
        },
        {
          "line": 1,
          "min_x": 333,
          "max_x": 392,
          "min_y": 94,
          "max_y": 140
        },
        {
          "line": 1,
          "min_x": 177,
          "max_x": 323,
          "min_y": 45,
          "max_y": 123
        },
        {
          "line": 1,
          "min_x": 67,
          "max_x": 171,
          "min_y": 54,
          "max_y": 147
        },
        {
          "line": 2,
          "min_x": 1082,
          "max_x": 1201,
          "min_y": 189,
          "max_y": 281
        },
        {
          "line": 2,
          "min_x": 1072,
          "max_x": 1072,
          "min_y": 163,
          "max_y": 189
        },
        {
          "line": 2,
          "min_x": 954,
          "max_x": 1068,
          "min_y": 183,
          "max_y": 277
        },
        {
          "line": 2,
          "min_x": 865,
          "max_x": 955,
          "min_y": 193,
          "max_y": 285
        },
        {
          "line": 2,
          "min_x": 742,
          "max_x": 861,
          "min_y": 179,
          "max_y": 270
        },
        {
          "line": 2,
          "min_x": 622,
          "max_x": 724,
          "min_y": 182,
          "max_y": 277
        }
      ]
    },
    {
      "sura": 3,
      "ayah": 39,
      "glyphs": [
        {
          "line": 2,
          "min_x": 474,
          "max_x": 623,
          "min_y": 190,
          "max_y": 257
        },
        {
          "line": 2,
          "min_x": 277,
          "max_x": 466,
          "min_y": 185,
          "max_y": 281
        },
        {
          "line": 2,
          "min_x": 184,
          "max_x": 270,
          "min_y": 190,
          "max_y": 270
        },
        {
          "line": 2,
          "min_x": 68,
          "max_x": 185,
          "min_y": 194,
          "max_y": 285
        },
        {
          "line": 3,
          "min_x": 1075,
          "max_x": 1200,
          "min_y": 328,
          "max_y": 415
        },
        {
          "line": 3,
          "min_x": 1025,
          "max_x": 1067,
          "min_y": 340,
          "max_y": 411
        },
        {
          "line": 3,
          "min_x": 837,
          "max_x": 1015,
          "min_y": 323,
          "max_y": 413
        },
        {
          "line": 3,
          "min_x": 779,
          "max_x": 824,
          "min_y": 318,
          "max_y": 396
        },
        {
          "line": 3,
          "min_x": 707,
          "max_x": 770,
          "min_y": 323,
          "max_y": 389
        },
        {
          "line": 3,
          "min_x": 563,
          "max_x": 700,
          "min_y": 320,
          "max_y": 408
        },
        {
          "line": 3,
          "min_x": 443,
          "max_x": 552,
          "min_y": 331,
          "max_y": 414
        },
        {
          "line": 3,
          "min_x": 296,
          "max_x": 436,
          "min_y": 306,
          "max_y": 405
        },
        {
          "line": 3,
          "min_x": 130,
          "max_x": 287,
          "min_y": 317,
          "max_y": 410
        },
        {
          "line": 3,
          "min_x": 67,
          "max_x": 127,
          "min_y": 331,
          "max_y": 402
        },
        {
          "line": 4,
          "min_x": 1132,
          "max_x": 1199,
          "min_y": 458,
          "max_y": 539
        },
        {
          "line": 4,
          "min_x": 976,
          "max_x": 1132,
          "min_y": 457,
          "max_y": 547
        },
        {
          "line": 4,
          "min_x": 794,
          "max_x": 970,
          "min_y": 461,
          "max_y": 537
        },
        {
          "line": 4,
          "min_x": 660,
          "max_x": 785,
          "min_y": 458,
          "max_y": 547
        },
        {
          "line": 4,
          "min_x": 597,
          "max_x": 656,
          "min_y": 461,
          "max_y": 539
        },
        {
          "line": 4,
          "min_x": 384,
          "max_x": 593,
          "min_y": 458,
          "max_y": 540
        },
        {
          "line": 4,
          "min_x": 261,
          "max_x": 363,
          "min_y": 448,
          "max_y": 543
        }
      ]
    },
    {
      "sura": 3,
      "ayah": 40,
      "glyphs": [
        {
          "line": 4,
          "min_x": 143,
          "max_x": 262,
          "min_y": 458,
          "max_y": 528
        },
        {
          "line": 4,
          "min_x": 68,
          "max_x": 143,
          "min_y": 464,
          "max_y": 548
        },
        {
          "line": 5,
          "min_x": 1150,
          "max_x": 1205,
          "min_y": 575,
          "max_y": 661
        },
        {
          "line": 5,
          "min_x": 1017,
          "max_x": 1135,
          "min_y": 583,
          "max_y": 670
        },
        {
          "line": 5,
          "min_x": 955,
          "max_x": 999,
          "min_y": 603,
          "max_y": 673
        },
        {
          "line": 5,
          "min_x": 848,
          "max_x": 947,
          "min_y": 583,
          "max_y": 686
        },
        {
          "line": 5,
          "min_x": 755,
          "max_x": 839,
          "min_y": 589,
          "max_y": 664
        },
        {
          "line": 5,
          "min_x": 632,
          "max_x": 744,
          "min_y": 591,
          "max_y": 681
        },
        {
          "line": 5,
          "min_x": 438,
          "max_x": 624,
          "min_y": 592,
          "max_y": 669
        },
        {
          "line": 5,
          "min_x": 257,
          "max_x": 429,
          "min_y": 583,
          "max_y": 678
        },
        {
          "line": 5,
          "min_x": 144,
          "max_x": 249,
          "min_y": 592,
          "max_y": 672
        },
        {
          "line": 5,
          "min_x": 144,
          "max_x": 142,
          "min_y": 561,
          "max_y": 587
        },
        {
          "line": 5,
          "min_x": 66,
          "max_x": 138,
          "min_y": 591,
          "max_y": 659
        },
        {
          "line": 6,
          "min_x": 1009,
          "max_x": 1203,
          "min_y": 719,
          "max_y": 805
        },
        {
          "line": 6,
          "min_x": 935,
          "max_x": 1004,
          "min_y": 726,
          "max_y": 790
        },
        {
          "line": 6,
          "min_x": 801,
          "max_x": 935,
          "min_y": 721,
          "max_y": 802
        },
        {
          "line": 6,
          "min_x": 751,
          "max_x": 794,
          "min_y": 730,
          "max_y": 796
        },
        {
          "line": 6,
          "min_x": 641,
          "max_x": 749,
          "min_y": 725,
          "max_y": 801
        },
        {
          "line": 6,
          "min_x": 527,
          "max_x": 629,
          "min_y": 714,
          "max_y": 809
        }
      ]
    },
    {
      "sura": 3,
      "ayah": 41,
      "glyphs": [
        {
          "line": 6,
          "min_x": 441,
          "max_x": 528,
          "min_y": 724,
          "max_y": 793
        },
        {
          "line": 6,
          "min_x": 352,
          "max_x": 433,
          "min_y": 730,
          "max_y": 811
        },
        {
          "line": 6,
          "min_x": 220,
          "max_x": 343,
          "min_y": 726,
          "max_y": 803
        },
        {
          "line": 6,
          "min_x": 168,
          "max_x": 215,
          "min_y": 724,
          "max_y": 808
        },
        {
          "line": 6,
          "min_x": 72,
          "max_x": 168,
          "min_y": 720,
          "max_y": 800
        },
        {
          "line": 6,
          "min_x": 70,
          "max_x": 72,
          "min_y": 694,
          "max_y": 719
        },
        {
          "line": 7,
          "min_x": 1134,
          "max_x": 1203,
          "min_y": 855,
          "max_y": 924
        },
        {
          "line": 7,
          "min_x": 983,
          "max_x": 1124,
          "min_y": 857,
          "max_y": 932
        },
        {
          "line": 7,
          "min_x": 907,
          "max_x": 970,
          "min_y": 843,
          "max_y": 923
        },
        {
          "line": 7,
          "min_x": 735,
          "max_x": 903,
          "min_y": 853,
          "max_y": 937
        },
        {
          "line": 7,
          "min_x": 593,
          "max_x": 728,
          "min_y": 852,
          "max_y": 930
        },
        {
          "line": 7,
          "min_x": 473,
          "max_x": 583,
          "min_y": 852,
          "max_y": 920
        },
        {
          "line": 7,
          "min_x": 354,
          "max_x": 460,
          "min_y": 848,
          "max_y": 941
        },
        {
          "line": 7,
          "min_x": 287,
          "max_x": 345,
          "min_y": 845,
          "max_y": 942
        },
        {
          "line": 7,
          "min_x": 192,
          "max_x": 285,
          "min_y": 857,
          "max_y": 936
        },
        {
          "line": 7,
          "min_x": 186,
          "max_x": 184,
          "min_y": 833,
          "max_y": 859
        },
        {
          "line": 7,
          "min_x": 68,
          "max_x": 180,
          "min_y": 843,
          "max_y": 932
        },
        {
          "line": 8,
          "min_x": 1102,
          "max_x": 1198,
          "min_y": 990,
          "max_y": 1069
        },
        {
          "line": 8,
          "min_x": 932,
          "max_x": 1097,
          "min_y": 986,
          "max_y": 1072
        },
        {
          "line": 8,
          "min_x": 771,
          "max_x": 926,
          "min_y": 992,
          "max_y": 1081
        },
        {
          "line": 8,
          "min_x": 617,
          "max_x": 761,
          "min_y": 990,
          "max_y": 1081
        },
        {
          "line": 8,
          "min_x": 356,
          "max_x": 612,
          "min_y": 988,
          "max_y": 1080
        },
        {
          "line": 8,
          "min_x": 238,
          "max_x": 340,
          "min_y": 980,
          "max_y": 1075
        }
      ]
    },
    {
      "sura": 3,
      "ayah": 42,
      "glyphs": [
        {
          "line": 8,
          "min_x": 167,
          "max_x": 239,
          "min_y": 990,
          "max_y": 1071
        },
        {
          "line": 8,
          "min_x": 70,
          "max_x": 161,
          "min_y": 983,
          "max_y": 1068
        },
        {
          "line": 9,
          "min_x": 956,
          "max_x": 1200,
          "min_y": 1113,
          "max_y": 1210
        },
        {
          "line": 9,
          "min_x": 805,
          "max_x": 942,
          "min_y": 1127,
          "max_y": 1217
        },
        {
          "line": 9,
          "min_x": 747,
          "max_x": 792,
          "min_y": 1125,
          "max_y": 1212
        },
        {
          "line": 9,
          "min_x": 669,
          "max_x": 734,
          "min_y": 1125,
          "max_y": 1187
        },
        {
          "line": 9,
          "min_x": 467,
          "max_x": 665,
          "min_y": 1124,
          "max_y": 1201
        },
        {
          "line": 9,
          "min_x": 273,
          "max_x": 453,
          "min_y": 1124,
          "max_y": 1203
        },
        {
          "line": 9,
          "min_x": 65,
          "max_x": 266,
          "min_y": 1123,
          "max_y": 1202
        },
        {
          "line": 10,
          "min_x": 1126,
          "max_x": 1197,
          "min_y": 1259,
          "max_y": 1336
        },
        {
          "line": 10,
          "min_x": 1014,
          "max_x": 1119,
          "min_y": 1259,
          "max_y": 1335
        },
        {
          "line": 10,
          "min_x": 766,
          "max_x": 1000,
          "min_y": 1253,
          "max_y": 1334
        },
        {
          "line": 10,
          "min_x": 648,
          "max_x": 750,
          "min_y": 1246,
          "max_y": 1341
        }
      ]
    },
    {
      "sura": 3,
      "ayah": 43,
      "glyphs": [
        {
          "line": 10,
          "min_x": 477,
          "max_x": 649,
          "min_y": 1263,
          "max_y": 1338
        },
        {
          "line": 10,
          "min_x": 375,
          "max_x": 476,
          "min_y": 1250,
          "max_y": 1343
        },
        {
          "line": 10,
          "min_x": 268,
          "max_x": 365,
          "min_y": 1256,
          "max_y": 1347
        },
        {
          "line": 10,
          "min_x": 69,
          "max_x": 262,
          "min_y": 1257,
          "max_y": 1337
        },
        {
          "line": 11,
          "min_x": 1051,
          "max_x": 1197,
          "min_y": 1387,
          "max_y": 1476
        },
        {
          "line": 11,
          "min_x": 986,
          "max_x": 1039,
          "min_y": 1393,
          "max_y": 1481
        },
        {
          "line": 11,
          "min_x": 760,
          "max_x": 976,
          "min_y": 1389,
          "max_y": 1470
        },
        {
          "line": 11,
          "min_x": 640,
          "max_x": 742,
          "min_y": 1379,
          "max_y": 1474
        }
      ]
    },
    {
      "sura": 3,
      "ayah": 44,
      "glyphs": [
        {
          "line": 11,
          "min_x": 525,
          "max_x": 641,
          "min_y": 1391,
          "max_y": 1469
        },
        {
          "line": 11,
          "min_x": 456,
          "max_x": 516,
          "min_y": 1399,
          "max_y": 1469
        },
        {
          "line": 11,
          "min_x": 353,
          "max_x": 447,
          "min_y": 1376,
          "max_y": 1465
        },
        {
          "line": 11,
          "min_x": 202,
          "max_x": 343,
          "min_y": 1386,
          "max_y": 1480
        },
        {
          "line": 11,
          "min_x": 67,
          "max_x": 192,
          "min_y": 1387,
          "max_y": 1478
        },
        {
          "line": 12,
          "min_x": 1097,
          "max_x": 1199,
          "min_y": 1519,
          "max_y": 1604
        },
        {
          "line": 12,
          "min_x": 1095,
          "max_x": 1084,
          "min_y": 1500,
          "max_y": 1524
        },
        {
          "line": 12,
          "min_x": 1009,
          "max_x": 1080,
          "min_y": 1525,
          "max_y": 1596
        },
        {
          "line": 12,
          "min_x": 894,
          "max_x": 993,
          "min_y": 1515,
          "max_y": 1589
        },
        {
          "line": 12,
          "min_x": 744,
          "max_x": 885,
          "min_y": 1519,
          "max_y": 1612
        },
        {
          "line": 12,
          "min_x": 699,
          "max_x": 736,
          "min_y": 1525,
          "max_y": 1606
        },
        {
          "line": 12,
          "min_x": 506,
          "max_x": 683,
          "min_y": 1515,
          "max_y": 1600
        },
        {
          "line": 12,
          "min_x": 343,
          "max_x": 494,
          "min_y": 1518,
          "max_y": 1616
        },
        {
          "line": 12,
          "min_x": 214,
          "max_x": 332,
          "min_y": 1510,
          "max_y": 1602
        },
        {
          "line": 12,
          "min_x": 69,
          "max_x": 207,
          "min_y": 1519,
          "max_y": 1600
        },
        {
          "line": 13,
          "min_x": 1093,
          "max_x": 1201,
          "min_y": 1663,
          "max_y": 1748
        },
        {
          "line": 13,
          "min_x": 1012,
          "max_x": 1082,
          "min_y": 1665,
          "max_y": 1729
        },
        {
          "line": 13,
          "min_x": 826,
          "max_x": 1006,
          "min_y": 1654,
          "max_y": 1720
        },
        {
          "line": 13,
          "min_x": 680,
          "max_x": 814,
          "min_y": 1654,
          "max_y": 1747
        },
        {
          "line": 13,
          "min_x": 633,
          "max_x": 670,
          "min_y": 1656,
          "max_y": 1740
        },
        {
          "line": 13,
          "min_x": 407,
          "max_x": 617,
          "min_y": 1655,
          "max_y": 1735
        },
        {
          "line": 13,
          "min_x": 283,
          "max_x": 385,
          "min_y": 1645,
          "max_y": 1740
        }
      ]
    },
    {
      "sura": 3,
      "ayah": 45,
      "glyphs": [
        {
          "line": 13,
          "min_x": 224,
          "max_x": 284,
          "min_y": 1659,
          "max_y": 1739
        },
        {
          "line": 13,
          "min_x": 67,
          "max_x": 214,
          "min_y": 1655,
          "max_y": 1735
        },
        {
          "line": 14,
          "min_x": 1009,
          "max_x": 1201,
          "min_y": 1778,
          "max_y": 1877
        },
        {
          "line": 14,
          "min_x": 860,
          "max_x": 997,
          "min_y": 1789,
          "max_y": 1883
        },
        {
          "line": 14,
          "min_x": 801,
          "max_x": 847,
          "min_y": 1786,
          "max_y": 1877
        },
        {
          "line": 14,
          "min_x": 725,
          "max_x": 791,
          "min_y": 1789,
          "max_y": 1855
        },
        {
          "line": 14,
          "min_x": 565,
          "max_x": 719,
          "min_y": 1787,
          "max_y": 1870
        },
        {
          "line": 14,
          "min_x": 418,
          "max_x": 554,
          "min_y": 1783,
          "max_y": 1873
        },
        {
          "line": 14,
          "min_x": 340,
          "max_x": 412,
          "min_y": 1788,
          "max_y": 1866
        },
        {
          "line": 14,
          "min_x": 221,
          "max_x": 331,
          "min_y": 1789,
          "max_y": 1854
        },
        {
          "line": 14,
          "min_x": 68,
          "max_x": 213,
          "min_y": 1786,
          "max_y": 1878
        },
        {
          "line": 15,
          "min_x": 1087,
          "max_x": 1203,
          "min_y": 1930,
          "max_y": 2003
        },
        {
          "line": 15,
          "min_x": 1020,
          "max_x": 1082,
          "min_y": 1924,
          "max_y": 1999
        },
        {
          "line": 15,
          "min_x": 911,
          "max_x": 1013,
          "min_y": 1928,
          "max_y": 2013
        },
        {
          "line": 15,
          "min_x": 784,
          "max_x": 904,
          "min_y": 1925,
          "max_y": 2010
        },
        {
          "line": 15,
          "min_x": 734,
          "max_x": 776,
          "min_y": 1937,
          "max_y": 2005
        },
        {
          "line": 15,
          "min_x": 612,
          "max_x": 728,
          "min_y": 1909,
          "max_y": 2000
        },
        {
          "line": 15,
          "min_x": 435,
          "max_x": 606,
          "min_y": 1914,
          "max_y": 2003
        },
        {
          "line": 15,
          "min_x": 348,
          "max_x": 434,
          "min_y": 1926,
          "max_y": 2004
        },
        {
          "line": 15,
          "min_x": 180,
          "max_x": 343,
          "min_y": 1914,
          "max_y": 2016
        },
        {
          "line": 15,
          "min_x": 65,
          "max_x": 167,
          "min_y": 1911,
          "max_y": 2006
        }
      ]
    }
  ]
}